iptables_xt_recent_parser-0.4.dist-info/RECORD
iptables_xt_recent_parser-0.4.dist-info/DESCRIPTION.rst
iptables_xt_recent_parser-0.4.dist-info/METADATA
iptables_xt_recent_parser-0.4.dist-info/top_level.txt
iptables_xt_recent_parser-0.4.dist-info/metadata.json
iptables_xt_recent_parser-0.4.dist-info/WHEEL
iptables_xt_recent_parser-0.4.data/scripts/iptables_xt_recent_parser.py
iptables_xt_recent_parser/iptables_xt_recent_parser.py
iptables_xt_recent_parser/__init__.py
