Metadata-Version: 2.0
Name: iptables-xt-recent-parser
Version: 0.4
Summary: Tool used for converting jiffies from iptables xt_recent into timestamps.
Home-page: https://github.com/peppelinux/iptables_xt_recent_parser
Author: Giuseppe De Marco
Author-email: giuseppe.demarco@unical.it
License: BSD
Platform: UNKNOWN
Classifier: Development Status :: 5 - Production/Stable
Classifier: License :: OSI Approved :: BSD License
Classifier: Programming Language :: Python :: 2
Classifier: Programming Language :: Python :: 3
